{"data":{"apps":{"appcoid":1444,"name":"OI App Center","website":"https://app-center.openintents.org","lifetimeEarnings":0,"openSourceUrl":"https://gitlab.com/friedger/appcenter","fields":{"lastCommit":"2019-06-03T16:06:57.000Z"}},"dec2018":{"totalCount":0,"edges":[]},"jan2019":{"totalCount":0,"edges":[]},"feb2019":{"totalCount":0,"edges":[]},"mar2019":{"totalCount":0,"edges":[]},"apr2019":{"totalCount":0,"edges":[]},"may2019":{"totalCount":0,"edges":[]},"june2019":{"totalCount":0,"edges":[]}},"pageContext":{"isCreatedByStatefulCreatePages":false,"appcoid":1444,"appname":"OI App Center"}}