{"data":{"apps":{"appcoid":1222,"name":"Cafe Society","website":"https://cafe-society.news/","lifetimeEarnings":0.27137089999999997,"openSourceUrl":"https://github.com/colealbon/cafe-society","fields":{"lastCommit":"Error on commit requests"}},"dec2018":{"totalCount":0,"edges":[]},"jan2019":{"totalCount":0,"edges":[]},"feb2019":{"totalCount":0,"edges":[]},"mar2019":{"totalCount":0,"edges":[]},"apr2019":{"totalCount":0,"edges":[]},"may2019":{"totalCount":0,"edges":[]},"june2019":{"totalCount":0,"edges":[]}},"pageContext":{"isCreatedByStatefulCreatePages":false,"appcoid":1222,"appname":"Cafe Society"}}