{"data":{"apps":{"appcoid":239,"name":"Entaxy","website":"https://entaxy.io/","lifetimeEarnings":8161.05177896,"openSourceUrl":"https://github.com/entaxy-project/entaxy","fields":{"lastCommit":"Error on commit requests"}},"dec2018":{"totalCount":0,"edges":[]},"jan2019":{"totalCount":0,"edges":[]},"feb2019":{"totalCount":0,"edges":[]},"mar2019":{"totalCount":0,"edges":[]},"apr2019":{"totalCount":0,"edges":[]},"may2019":{"totalCount":0,"edges":[]},"june2019":{"totalCount":0,"edges":[]}},"pageContext":{"isCreatedByStatefulCreatePages":false,"appcoid":239,"appname":"Entaxy"}}